{
  "seg_id": "PKD-SEG-VALISTRI-P0347",
  "work_id": "PKD-WRK-1981-VALISTRI",
  "title": "The VALIS Trilogy \u2014 Page 347",
  "segment_type": "page",
  "position": 347,
  "page_start": 347,
  "page_end": 347,
  "raw_text": "prisoner; loose a tide of murderers on the world. You have begun with me.\nAgain I thank you. But now I leave you; I have as much to do as you have\u2014\nperhaps more. Let me down.\u201d The goat leaped from their arms and ran off;\nZina and Emmanuel watched it go. And as it ran it grew.\n\u201cIt will undo our world,\u201d Zina said.\nEmmanuel said, \u201cWe will kill it first.\u201d He raised his hand; the goat\nvanished.\n\u201cIt is not gone,\u201d Zina said. \u201cIt has concealed itself in the world.\nCamouflaged itself. We cannot now even find it. You know that it won\u2019t die.\nLike us it is eternal.\u201d\nIn the other cages the remaining imprisoned animals clamored to be\nreleased. Zina and Emmanuel ignored them; instead, they looked this way and\nthat for the goat whom they had let out\u2014let out to do as it wished,\n\u201cI sense its presence,\u201d Zina said.\n\u201cI, too,\u201d Emmanuel said somberly. \u201cOur work is undone already.\u201d\n\u201cBut the battle is not over,\u201d Zina said. \u201cAs it said itself, \u2018The battle now\nbegins.\u2019\u201d\n\u201cSo be it,\u201d Emmanuel said. \u201cWe will fight it together, the two of us. As we\ndid in the beginning, before the fall.\u201d\nLeaning toward him, Zina kissed him.\nHe felt her fear. Her intense dread. And that dread lay within him, too.\nWhat will become of them now? he asked himself. The people whom he\nwished to free. What kind of prison will Belial contrive for them with his\nendless ability to contrive prisons? Subtle ones and gross ones, prisons within\nprisons; prisons for the body, and, worse by far, prisons for the mind.\nThe Cave of Treasures under the Garden: dark and small, without air and\nwithout light, without real time and real space\u2014walls that shrink and, caught\ntight, minds that shrink. And we have allowed this, Zina and I; we have\ncolluded with the goat-thing to bring this about.\nIts release is their constraint, he realized. A paradox; we have given freedom\nto the builder of dungeons. In our desire to emancipate we have crushed the\nsouls of all the living.\nIt will affect every one of them in this world, from the highest to the lowest.\nUntil we can return the goat-thing to its box; until we can place it back within\nits container.\nAnd now it is everywhere; it is not contained. The atoms of the air are now\nits abode; it is inhaled like vapor. And each creature, breathing it in, will die.\nNot completely and not physically, but nonetheless death will come. We have\nreleased death, the death of the spirit. For all that now lives and wishes to\nlive. This is our gift to them, done out of kindness.\n\u201cMotive does not count,\u201d Zina said, aware of his thoughts.\nEmmanuel said, \u201cThe road to hell.\u201d Literally, he thought, in this case. That\n",
  "word_count": 481,
  "work_title": "The VALIS Trilogy",
  "work_slug": "the-valis-trilogy",
  "prev_seg_id": "PKD-SEG-VALISTRI-P0346",
  "next_seg_id": "PKD-SEG-VALISTRI-P0348"
}