{
  "seg_id": "PKD-SEG-EXEGESIS-P0894",
  "work_id": "PKD-WRK-1974-EXEGESIS",
  "title": "The Exegesis of Philip K. Dick \u2014 Page 894",
  "segment_type": "page",
  "position": 894,
  "page_start": 894,
  "page_end": 894,
  "raw_text": "encroaching madness, but VALIS is a lucid postmortem, a deliberate and\nrational study, of this issue, this battle, and the victory of the rational in me\n(expressed as Valis, logos or Christ). The one who sees precisely all this\u2014the\nbattle and the victory and even the cause of the ominous issue or problem (a\ndecade of intense suffering and trial)\u2014is John Clute writing in the Post. I\ncame through it and emerged victorious: but just barely.\n \n[54:M-29] I guess my realization came (last night) when, after reading Pot\nand realizing that I did become psychotic, I then picked up Scanner and read\nhere and there. The appalling horror of that book! To go into that from\npsychosis; that is, how terrible a fate awaited me. What saved me was my\nlove for those people: Luckman (Ray Harris), Jerry Fabin (Dennis) and\nDonna (Kathy), which ties in with Tears and the scene at the all-night gas\nstation.\nThinking back to when I wrote Pot: I felt so strongly\u2014and correctly\u2014 at\nthe time that when it came time, in writing the book, to have the theophany\noccur (i.e., for Glimmung to show himself) I had nothing to say, nothing to\noffer because I knew nothing.65 Oh, and how I sensed this lack of knowledge!\nAnd now this is precisely what I do know because now I have experienced it\n(2-3-74).\nIn a way I better depict the 3-74 theophany (of Valis) in DI than in VALIS\nitself. In any case if you superimpose the two novels it is there\u2014precisely\nwhat I lacked when I wrote Pot\u2014and knew I lacked, as a human, as a writer; I\nhad no ideas about the theophany at all, and yet by the time I wrote DI it came\neasily, that which would not and could not come with Pot; thus in writing Pot\nthat exactly was where I reached the end\u2014wore out and died as a writer;\nscraped the bottom of the barrel and died creatively and spiritually. What\nmisery that was! Paisley shawl, hoop of water, hoop of fire; how wretched it\nwas; how futile.\nStrange that later (1974) I experienced what I had yearned to know so that\nI could continue the logical, organic growth and forward development of my\nwriting. That was where I wore out: trying to depict a theophany. And that is\nwhat I legitimately later on (in the VALIS trilogy) could do. But oh the years\nof suffering! And yet\u2014if I became psychotic in writing Pot\u2014if Pot shows\nsigns of psychosis, and it does\u2014it is not because I experienced and knew God\nbut precisely because I did not. And thus the Valis books are the opposite, are\nsane, are grounded in experience and in reality because by then I had\nexperienced God; hence my creative life (not just my spiritual life) resumed;\nand with it my sanity. Thus in a very real sense my sanity depended on my\nexperiencing God, because my creative life logically demanded it\u2014and as\n",
  "word_count": 498,
  "work_title": "The Exegesis of Philip K. Dick",
  "work_slug": "the-exegesis-of-philip-k-dick",
  "prev_seg_id": "PKD-SEG-EXEGESIS-P0893",
  "next_seg_id": "PKD-SEG-EXEGESIS-P0895"
}