{
  "seg_id": "PKD-SEG-EXEGESIS-P0414",
  "work_id": "PKD-WRK-1974-EXEGESIS",
  "title": "The Exegesis of Philip K. Dick \u2014 Page 414",
  "segment_type": "page",
  "position": 414,
  "page_start": 414,
  "page_end": 414,
  "raw_text": "us, Brahman plays tricks and games in conjuring up any and all worlds\u2014X\nnumber of them, one for each individual Atman, which means billions\u2014and\neach Atman finds its exterior analog perfectly substantial, real, consistent,\nsatisfactory and objective (but: compared to what, I ask).\n \n[2:30] I have been governed too much by my own fictional models (e.g.,\nMaze, Joint).\n \n[2:36] So our little psyche-world systems are perpetually bombarded with\nincoming information which we process and, at the right time to the right\nother stations we transmit in the rightly modified form\u2014but all this takes\nplace through us as if we were transistors, diodes, wires condensers and\nresistors, all none the wiser. Meanwhile our closed private world engages our\nattention with challenges, pain and delight, so that we will not merely subsist\nas slave components with nothing to do but function. After all, there will be\nlong intervals when no adventitious information needs to be processed by us\n\u2014without a world, we would degenerate fatally during the standby periods,\nwhich, I intuit, may last years or even decades. Meanwhile we have food,\nmusic, books and friends.\nThe primal necessity of this info processing may explain events and\nepisodes in our lives which otherwise remain enigmatic or appear even futile\n\u2014pointless travail, goalless activity. For all we know, it is during or because\nof these that we then or later can fulfill our data processing task. I'm not sure\nof this but I suspect it.* [...]\nI have read these 37 pages over and I'm amazed and delighted at the\ndirection of my analysis. What an original system\u2014and, more important, a\nsystem at last commensurate with the revelations of 3-74. Always before, the\nexegesis plainly fell short of the experience it served to explain, or tried to\nexplain. But at last, by the aid of the voice I have made bold clean strokes,\nradical ones, in this B model. After reading it over I can't fault it. Such wild\ndisclosures as those of 3-74 require a wild explanation, not a conventional or\ncustomary one.\n \n[2:41] This is the paradox of \"where should you most expect to find God?\" A:\n\"in the least likely place.\" I discern in this the following: \"in point of fact you\ntherefore cannot find God at all; he must\u2014will\u2014find you, and when and\nwhere you least expect it\"\u2014i.e., he will take you by surprise, like the still\nsmall voice which Elijah heard. Or like Oh Ho the ceramic pot. The Oracle\nmay speak to you from the gutter (whatever \"gutter\" might mean in this\ncontext).\n",
  "word_count": 426,
  "work_title": "The Exegesis of Philip K. Dick",
  "work_slug": "the-exegesis-of-philip-k-dick",
  "prev_seg_id": "PKD-SEG-EXEGESIS-P0413",
  "next_seg_id": "PKD-SEG-EXEGESIS-P0415"
}