{
  "seg_id": "PKD-SEG-UBIK-P0120",
  "work_id": "PKD-WRK-1969-UBIK",
  "title": "Ubik \u2014 Page 120",
  "segment_type": "page",
  "position": 120,
  "page_start": 120,
  "page_end": 120,
  "raw_text": "room; he propelled Joe out into the corridor. \u201cGo on, make \nsure they\u2019re all right!\u201d Al retreated back into the men\u2019s \nroom, clutching at his own eyes; bent over, he disappeared \nfrom view as the door swung shut. \n     Joe hesitated. \u201cOkay,\u201d he said, \u201cI\u2019ll be in the conference \nroom with them.\u201d He waited, listening; heard nothing. \u201cAl?\u201d \nhe said. Christ, he thought. This is terrible. Something is \nreally the matter with him. \u201cI want to see with my own \neyes,\u201d he said, pushing against the door, \u201cthat you\u2019re all \nright.\u201d \n     In a low, calm voice Al said, \u201cIt\u2019s too late, Joe. Don\u2019t \nlook.\u201d The men\u2019s room had become dark; Al evidently had \nmanaged to turn the light off. \u201cYou can\u2019t do anything to help \nme,\u201d he said in a weak but steady voice. \u201cWe shouldn\u2019t have \nseparated from the others; that\u2019s why it happened to \nWendy. You can stay alive at least for a while if you go find \nthem and stick with them. Tell them that; make sure all of \nthem understand. Do you understand?\u201d \n     Joe reached for the light switch. \n     A blow, feeble and weightless, cuffed his hand in the \ndarkness; terrified, he withdrew his hand, shocked by the \nimpotence of Al\u2019s punch. It told him everything. He no \nlonger needed to see. \n     \u201cI\u2019ll go join the others,\u201d he said. \u201cYes, I understand. Does \nit feel very bad?\u201d \n     Silence, and then a listless voice whispered, \u201cNo, it \ndoesn\u2019t feel very bad. I just-\u201d The voice faded out. Once \nmore only silence. \n     \u201cMaybe I\u2019ll see you again sometime,\u201d Joe said. He knew \nit was the wrong thing to say - it horrified him to hear \nhimself prattle out such an inanity. But it was the best he \ncould do. \u201cLet me put it another way,\u201d he said, but he knew \nAl could no longer hear him. \u201cI hope you feel better,\u201d he \nsaid. \u201cI\u2019ll check back after I tell them about the writing on \nthe wall in there. I\u2019ll tell them not to come in here and look \nat it because it might-\u201d He tried to think it out, to say it \nright. \u201cThey might bother you,\u201d he finished. \n     No response. \n",
  "word_count": 362,
  "work_title": "Ubik",
  "work_slug": "ubik",
  "prev_seg_id": "PKD-SEG-UBIK-P0119",
  "next_seg_id": "PKD-SEG-UBIK-P0121"
}