{
  "seg_id": "PKD-SEG-EXEGESIS-P0977",
  "work_id": "PKD-WRK-1974-EXEGESIS",
  "title": "The Exegesis of Philip K. Dick \u2014 Page 977",
  "segment_type": "page",
  "position": 977,
  "page_start": 977,
  "page_end": 977,
  "raw_text": "to Charles Freck, only to himself. To his own vital, demanding, terrible,\nurgent needs. Everything else would have to wait. There was no time, no\ntime; these things could not be postponed. Everything else was secondary.\nExcept the dog; he wondered about Max, the dog.\n \nCharles Freck phoned up somebody who he hoped was holding. \"Can you lay\nabout ten deaths on me?\"\n\"Christ, I'm entirely out\u2014I'm looking to score myself. Let me know when\nyou find some, I could use some.\"\n\"What's wrong with the supply?\"\n\"Some busts, I guess.\"\nCharles Freck hung up and then ran a fantasy number in his head as he\nslumped dismally back from the pay phone booth\u2014you never used your\nhome phone for a buy call\u2014to his parked Chevy. In his fantasy number he\nwas driving past the Thrifty Drugstore and they had a huge window display;\nbottles of slow death, cans of slow death, jars and bathtubs and vats and\nbowls of slow death, millions of caps and tabs and hits of slow death, slow\ndeath mixed with speed and junk and barbiturates and psychedelics,\neverything\u2014and a giant sign: YOUR CREDIT IS GOOD HERE. Not to mention: LOW\nLOW PRICES, LOWEST IN TOWN.\nBut in actuality the Thrifty usually had a display of nothing: combs,\nbottles of mineral oil, spray cans of deodorant, always crap like that. But I bet\nthe pharmacy in the back has slow death under lock and key in an unstepped-\non, pure, unadulterated, uncut form, he thought as he drove from the parking\nlot onto Harbor Boulevard, into the afternoon traffic. About a fifty-pound bag.\nHe wondered when and how they unloaded the fifty-pound bag of\nSubstance D at the Thrifty Pharmacy every morning, from wherever it came\nfrom\u2014God knew, maybe from Switzerland or maybe from another planet\nwhere some wise race lived. They'd deliver probably real early, and with\narmed guards\u2014the Man standing there with Laser rifles looking mean, the\nway the Man always did. Anybody rip off my slow death, he thought through\nthe Man's head, I'll snuff them.\nProbably Substance D is an ingredient in every legal medication that's\nworth anything, he thought. A little pinch here and there according to the\nsecret exclusive formula at the issuing house in Germany or Switzerland that\ninvented it. But in actuality he knew better; the authorities snuffed or sent up\neverybody selling or transporting or using, so in that case the Thrifty\nDrugstore\u2014all the millions of Thrifty Drugstores\u2014would get shot or bombed\nout of business or anyhow fined. More likely just fined. The Thrifty had pull.\nAnyhow, how do you shoot a chain of big drugstores? Or put them away?\n",
  "word_count": 444,
  "work_title": "The Exegesis of Philip K. Dick",
  "work_slug": "the-exegesis-of-philip-k-dick",
  "prev_seg_id": "PKD-SEG-EXEGESIS-P0976",
  "next_seg_id": "PKD-SEG-EXEGESIS-P0978"
}