{
  "seg_id": "PKD-SEG-UBIK-P0081",
  "work_id": "PKD-WRK-1969-UBIK",
  "title": "Ubik \u2014 Page 81",
  "segment_type": "page",
  "position": 81,
  "page_start": 81,
  "page_end": 81,
  "raw_text": "human values and compassion and simple warmth will \nreturn, and when that happens someone like myself who has \ngone through an ordeal and who genuinely needs hot coffee \nto pick him up and keep him functioning when he has to \nfunction will get the hot coffee whether he happens to have \na poscred readily available or not.\u201d He lifted the miniature \npitcher of cream, then set it down. \u201cAnd furthermore, your \ncream or milk or whatever it is, is sour.\u201d \n     The speaker remained silent. \n     \u201cAren\u2019t you going to do anything?\u201d Joe said. \u201cYou had \nplenty to say when you wanted a poscred.\u201d \n \n     The pay door of the coffee shop opened and Al Hammond \ncame in; he walked over to Joe and seated himself beside \nhim. \u201cThe moratorium has Runciter in their chopper. They\u2019re \nready to take off and they want to know if you intend to ride \nwith them.\u201d \n     Joe said, \u201cLook at this cream.\u201d He held up the pitcher; in \nit the fluid plastered the sides in dense clots. \u201cThis is what \nyou get for a poscred in one of the most modern, \ntechnologically advanced cities on Earth. I\u2019m not leaving \nhere until this place makes an adjustment, either returning \nmy poscred or giving me a replacement pitcher of fresh \ncream so I can drink my coffee.\u201d \n     Putting his hand on Joe\u2019s shoulder, Al Hammond studied \nhim. \u201cWhat\u2019s the matter, Joe?\u201d \n     \u201cFirst my cigarette,\u201d Joe said. \u201cThen the two-year-old \nobsolete phone book in the ship. And now they\u2019re serving \nme week-old sour cream. I don\u2019t get it, Al.\u201d \n     \u201cDrink the coffee black,\u201d Al said. \u201cAnd get over to the \nchopper so they can take Runciter to the moratorium. The \nrest of us will wait in the ship until you come back. And then \nwe\u2019ll head for the nearest Society office and make a full \nreport to them.\u201d \n     Joe picked up the coffee cup, and found the coffee cold, \ninert and ancient; a scummy mold covered the surface. He \nset the cup back down in revulsion. What\u2019s going on? he \nthought. What\u2019s happening to me? His revulsion became, all \n",
  "word_count": 349,
  "work_title": "Ubik",
  "work_slug": "ubik",
  "prev_seg_id": "PKD-SEG-UBIK-P0080",
  "next_seg_id": "PKD-SEG-UBIK-P0082"
}