{
  "seg_id": "PKD-SEG-UBIK-P0004",
  "work_id": "PKD-WRK-1969-UBIK",
  "title": "Ubik \u2014 Page 4",
  "segment_type": "page",
  "position": 4,
  "page_start": 4,
  "page_end": 4,
  "raw_text": "Melipone\u2019s mind, so he couldn\u2019t do anything; he therefore \nwent back to Topeka, Kansas, where he\u2019s currently scouting \na new possibility.\u201d \n     Runciter, more awake now, had lit a cigarette; chin in \nhand, he sat propped up somberly, smoke drifting across the \nscanner of his end of the bichannel circuit. \u201cYou\u2019re sure the \nteep was Melipone? Nobody seems to know what he looks \nlike; he must use a different physiognomic template every \nmonth. What about his field?\u201d \n     \u201cWe asked Joe Chip to go in there and run tests on the \nmagnitude and minitude of the field being generated there \nat the Bonds of Erotic Polymorphic Experience Motel. Chip \nsays it registered, at its height, 68.2 blr units of telepathic \naura, which only Melipone, among all the known telepaths, \ncan produce.\u201d The technician finished, \u201cSo that\u2019s where we \nstuck Melipone\u2019s identflag on the map. And now he - it - is \ngone.\u201d \n     \u201cDid you look on the floor? Behind the map?\u201d \n     \u201cIt\u2019s gone electronically. The man it represents is no \nlonger on Earth or, as far as we can make out, on a colony \nworld either.\u201d \n     Runciter said, \u201cI\u2019ll consult my dead wife.\u201d \n     \u201cIt\u2019s the middle of the night. The moratoriums are closed \nnow.\u201d \n     \u201cNot in Switzerland,\u201d Runciter said, with a grimacing \nsmile, as if some repellent midnight fluid had crept up into \nhis aged throat. \u201cGoodeve.\u201d Runciter hung up. \n     As owner of the Beloved Brethren Moratorium, Herbert \nSchoenheit von Vogelsang, of course, perpetually came to \nwork before his employees. At this moment, with the chilly, \nechoing building just beginning to stir, a worried-looking \nclerical individual with nearly opaque glasses and wearing a \ntabby-fur blazer and pointed yellow shoes waited at the \nreception counter, a claim-check stub in his hand. Obviously, \nhe had shown up to holiday-greet a relative. Resurrection \nDay - the holiday on which the half-lifers were publicly \nhonored - lay just around the corner; the rush would soon \nbe beginning. \n",
  "word_count": 321,
  "work_title": "Ubik",
  "work_slug": "ubik",
  "prev_seg_id": "PKD-SEG-UBIK-P0003",
  "next_seg_id": "PKD-SEG-UBIK-P0005"
}