{
  "seg_id": "PKD-SEG-EXEGESIS-P0966",
  "work_id": "PKD-WRK-1974-EXEGESIS",
  "title": "The Exegesis of Philip K. Dick \u2014 Page 966",
  "segment_type": "page",
  "position": 966,
  "page_start": 966,
  "page_end": 966,
  "raw_text": "Westaway, Jim, [>]\nWhitehead, Alfred North, [>], [>], [>], [>], [>]\nWiggins, Charles, [>]\nWilliams, Paul, [>]\u2013[>], [>]\nWilson, Bob, [>], [>]\nWilson, Robert Anton, [>], [>]\nWittgenstein, Ludwig, [>]\nWordsworth, William, [>], [>], [>], [>]\nWunderlich, Fritz, [>]\nXenophanes, [>], [>]\u2013[>], [>], [>]\nYeats, William Butler, [>], [>]\nZimmer, Heinrich, [>]\n",
  "word_count": 52,
  "work_title": "The Exegesis of Philip K. Dick",
  "work_slug": "the-exegesis-of-philip-k-dick",
  "prev_seg_id": "PKD-SEG-EXEGESIS-P0965",
  "next_seg_id": "PKD-SEG-EXEGESIS-P0967"
}