{
  "seg_id": "PKD-SEG-VALISTRI-P0010",
  "work_id": "PKD-WRK-1981-VALISTRI",
  "title": "The VALIS Trilogy \u2014 Page 10",
  "segment_type": "page",
  "position": 10,
  "page_start": 10,
  "page_end": 10,
  "raw_text": "1\nHORSELOVER FAT\u2019S NERVOUS breakdown began the day he got the phone call\nfrom Gloria asking if he had any Nembutals. He asked her why she wanted\nthem and she said that she intended to kill herself. She was calling everyone\nshe knew. By now she had fifty of them, but she needed thirty or forty more\nto be on the safe side.\nAt once Horselover Fat leaped to the conclusion that this was her way of\nasking for help. It had been Fat\u2019s delusion for years that he could help people.\nHis psychiatrist once told him that to get well he would have to do two things;\nget off dope (which he hadn\u2019t done) and to stop trying to help people (he still\ntried to help people).\nAs a matter of fact, he had no Nembutals. He had no sleeping pills of any\nsort. He never did sleeping pills. He did uppers. So giving Gloria sleeping\npills by which she could kill herself was beyond his power. Anyhow, he\nwouldn\u2019t have done it if he could.\n\u201cI have ten,\u201d he said. Because if he told her the truth she would hang up.\n\u201cThen I\u2019ll drive up to your place,\u201d Gloria said in a rational, calm voice, the\nsame tone in which she had asked for the pills.\nHe realized then that she was not asking for help. She was trying to die. She\nwas completely crazy. If she were sane she would realize that it was necessary\nto veil her purpose, because this way she made him guilty of complicity. For\nhim to agree, he would need to want her dead. No motive existed for him\u2014or\nanyone\u2014to want that. Gloria was gentle and civilized, but she dropped a lot\nof acid. It was obvious that the acid, since he had last heard from her six\nmonths ago, had wrecked her mind.\n\u201cWhat\u2019ve you been doing?\u201d Fat asked.\n\u201cI\u2019ve been in Mount Zion Hospital in San Francisco. I tried suicide and my\nmother committed me. They discharged me last week.\u201d\n\u201cAre you cured?\u201d he said.\n\u201cYes,\u201d she said.\nThat\u2019s when Fat began to go nuts. At the time he didn\u2019t know it, but he had\nbeen drawn into an unspeakable psychological game. There was no way out.\nGloria Knudson had wrecked him, her friend, along with her own brain.\nProbably she had wrecked six or seven other people, all friends who loved\nher, along the way, with similar phone conversations. She had undoubtedly\ndestroyed her mother and father as well. Fat heard in her rational tone the\nharp of nihilism, the twang of the void. He was not dealing with a person; he\nhad a reflex-arc thing at the other end of the phone line.\nWhat he did not know then is that it is sometimes an appropriate response to\nreality to go insane. To listen to Gloria rationally ask to die was to inhale the\n",
  "word_count": 486,
  "work_title": "The VALIS Trilogy",
  "work_slug": "the-valis-trilogy",
  "prev_seg_id": "PKD-SEG-VALISTRI-P0009",
  "next_seg_id": "PKD-SEG-VALISTRI-P0011"
}