{
  "seg_id": "PKD-SEG-EXEGESIS-P0695",
  "work_id": "PKD-WRK-1974-EXEGESIS",
  "title": "The Exegesis of Philip K. Dick \u2014 Page 695",
  "segment_type": "page",
  "position": 695,
  "page_start": 695,
  "page_end": 695,
  "raw_text": "topic in Scanner is the topic of VALIS, but now it is an ontological cosmic\nocclusion: insane creator and irrational creation. The cure (remedy) is\nsalvation through Christ who, it is stipulated, represents the principle of\nrationality; he breaks into the universe, heals it and us as antidote, and\ninvisibly transubstantiates the universe into his own body. Yet, paradoxically,\nChrist himself has been wounded by the Black Iron Prison, the Empire,\nthrough its spear; as he is physician and savior to us we ourselves flock to\ndestroy the Empire and heal our own savior (salvador salvandus).\n[...]\nScanner is my true Paradise Lost (the story of the Fall) and VALIS\nParadise Regained, the story of the restoration through Christ. Hence VALIS\ncan only be truly understood if Scanner is taken into account. Bob Arctor on\nthe last page of Scanner is Horselover Fat on the first page of VALIS\u2014the two\nnovels form a seamless whole.\n \n(1) Scanner: Man's fall into occlusion, ignorance, impairment and\nenslavement.\u278a\n(2)VALIS: Man's restoration through Christ who brings him the\nsaving Gnosis that in effect he has lost (been deprived of).\u278b\n \n\u278a Here he, the man, splits into two halves: he is self-estranged. He is\nwounded.\n\u278b Here he, the man, fuses back together as one intact person; the wound\nhas healed. He now recognizes himself as himself. The saving knowledge\n(gnosis) takes the form of man's ability to identify a picture of himself as\nhimself (\"Mein eigenes Gesicht\") (or: \"Mein eigenes Gestalt\"1). Thus\ntopologically the universe that in Scanner was pulled through infinity,\nreversing the gestalt and making it unfamiliar (i.e., Fremd), has been reversed\nonce more and is its familiar self: nicht Fremd but rather Heimlich. The\nGnostic categories of estrangement and alienation versus returning to one's\nhome, the familiar, apply here. One has come to oneself after the Fall in\nScanner.\n \n[89:103] It is very, very important to realize that in Tears two distinct selves\nin me were writing two parallel but unconnected narratives: (1) the overt,\nexplicated political one about forced labor camps and a U.S. ruled by five\npolice marshals, the pols and nats; and (2) a latent religious narrative about\nChrist and Rome and St. Paul\u2014and agape. Now, in 2-3-74, these two selves\nas (so to speak) thesis and antithesis ignited into one single ultra synthesis in\nwhich the apparently conflicting elements that divided them off from each\n",
  "word_count": 398,
  "work_title": "The Exegesis of Philip K. Dick",
  "work_slug": "the-exegesis-of-philip-k-dick",
  "prev_seg_id": "PKD-SEG-EXEGESIS-P0694",
  "next_seg_id": "PKD-SEG-EXEGESIS-P0696"
}