{
  "seg_id": "PKD-SEG-VALISTRI-P0364",
  "work_id": "PKD-WRK-1981-VALISTRI",
  "title": "The VALIS Trilogy \u2014 Page 364",
  "segment_type": "page",
  "position": 364,
  "page_start": 364,
  "page_end": 364,
  "raw_text": "again they remained locked in place.\nLet us reason, the goat-creature thought to him. This is my view of the\nworld and I will make it your view and the view of everyone. It is the truth.\nThe light that shone originally was a spurious light. That light is going out\nand the true nature of reality is disclosed in its absence. That light blinded\nmen to the real state of things. It is my job to reveal that real state.\nGray truth, the goat-creature continued, is better than what you have\nimagined. You wanted to wake up. Now you are awake; I show you things as\nthey are, pitilessly; but that is how it should be. How do you suppose I\ndefeated Yahweh in times past? By revealing his creation for what it is, a\nwretched thing to be despised. This is his defeat, what you see\u2014see through\nmy mind and eyes, my vision of the world: my correct vision. Recall Rybys\nRommey\u2019s dome, the way it was when you first saw it; remember what she\nwas like; consider what she is like now. Do you suppose that Linda Fox is any\ndifferent? Or that you are any different? You are all the same, and when you\nsaw the debris and spoiled food and rotting matter of Rybys\u2019s dome you saw\nhow reality really is. You saw life. You saw the truth.\nI will soon show you that truth about the Fox, the goat-creature continued.\nThat is what you will find at the end of this trip: exactly what you found in\nRybys Rommey\u2019s deteriorated dome that day, years ago. Nothing has changed\nand nothing is different. You could not escape it then and you cannot escape it\nnow.\nWhat do you say to that? the goat-creature asked him.\n\u201cThe future need not resemble the past,\u201d Herb Asher said.\nNothing changes, the goat-creature answered. Scripture itself tells us that.\n\u201cEven a goat can cite Scripture,\u201d Herb Asher said.\nThey entered the heavy stream of air traffic routed toward the Los Angeles\narea; cars and commercial vehicles moved on all sides of them, above them,\nbelow them. Herb Asher could discern police cars but none paid him any\nattention.\nI will guide you to her house, the goat-creature informed him.\n\u201cCreature of dirt,\u201d Herb Asher said, with fury.\nA floating signal pointed the way ahead. They had almost reached\nCalifornia.\n\u201cI will wager with you that\u2014\u201d Herb Asher began, but the goat-creature cut\nhim off.\nI do not wager, it thought to him. I do not play. I am the strong and I prey on\nthe weak. You are the weak, and Linda Fox is weaker yet. Forget the idea of\ngames; that is for children.\n\u201cYou must be like a little child,\u201d Herb Asher said, \u201cto enter the Kingdom of\nGod.\u201d\nI have no interest in that kingdom, the goat-thing thought to him. This is my\n",
  "word_count": 487,
  "work_title": "The VALIS Trilogy",
  "work_slug": "the-valis-trilogy",
  "prev_seg_id": "PKD-SEG-VALISTRI-P0363",
  "next_seg_id": "PKD-SEG-VALISTRI-P0365"
}