{
  "seg_id": "PKD-SEG-VALISTRI-P0189",
  "work_id": "PKD-WRK-1981-VALISTRI",
  "title": "The VALIS Trilogy \u2014 Page 189",
  "segment_type": "page",
  "position": 189,
  "page_start": 189,
  "page_end": 189,
  "raw_text": "Also, the teaching function was grossly impaired, since only the signal from\nthe hyperuniverse I was information-rich; that from II had become noise.\nThe psyche of hyperuniverse I sent a micro-form of itself into\nhyperuniverse II to attempt to heal it. The micro-form was apparent in our\nhologramatic universe as Jesus Christ. However, hyperuniverse II, being\nderanged, at once tormented, humiliated, rejected and finally killed the micro-\nform of the healing psyche of her healthy twin. After that, hyperuniverse II\ncontinued to decay into blind, mechanical, purposeless causal processes. It\nthen became the task of Christ (more properly the Holy Spirit) to either rescue\nthe life forms in the hologramatic universe, or abolish all influences on it\nemanating from II. Approaching its task with caution, it prepared to kill the\nderanged twin, since she cannot be healed; i.e., she will not allow herself to\nbe healed because she does not understand that she is sick. This illness and\nmadness pervades us and makes us idiots living in private, unreal worlds. The\noriginal plan of the One can only be realized now by the division of\nhyperuniverse I into two healthy hyperuniverses, which will transform the\nhologramatic universe into the successful teaching machine it was designed to\nbe. We will experience this as the \u201cKingdom of God.\u201d\nWithin time, hyperuniverse II remains alive: \u201cThe Empire never ended.\u201d\nBut in eternity, where the hyperuniverses exist, she has been killed\u2014of\nnecessity\u2014by the healthy twin of hyperuniverse I, who is our champion. The\nOne grieves for this death, since the One loved both twins; therefore the\ninformation of the Mind consists of a tragic tale of the death of a woman, the\nundertones of which generate anguish into all the creatures of the\nhologramatic universe without their knowing why. This grief will depart when\nthe healthy twin undergoes mitosis and the \u201cKingdom of God\u201d arrives. The\nmachinery for this transformation\u2014the procession within time from the Age\nof Iron to the Age of Gold\u2014is at work now; in eternity it is already\naccomplished.\n \n48. ON OUR NATURE. It is proper to say: we appear to be memory coils (DNA\ncarriers capable of experience) in a computer-like thinking system which,\nalthough we have correctly recorded and stored thousands of years of\nexperiential information, and each of us possesses somewhat different\ndeposits from all the other life forms, there is a malfunction\u2014a failure\u2014of\nmemory retrieval. There lies the trouble in our particular subcircuit.\n\u201cSalvation\u201d through gnosis\u2014more properly anamnesis (the loss of amnesia)\n\u2014although it has individual significance for each of us\u2014a quantum leap in\nperception, identity, cognition, understanding, world- and self-experience,\nincluding immortality\u2014it has greater and further importance for the system as\na whole, inasmuch as these memories are data needed by it and valuable to it,\nto its overall functioning.\n",
  "word_count": 464,
  "work_title": "The VALIS Trilogy",
  "work_slug": "the-valis-trilogy",
  "prev_seg_id": "PKD-SEG-VALISTRI-P0188",
  "next_seg_id": "PKD-SEG-VALISTRI-P0190"
}