{
  "seg_id": "PKD-SEG-VALISTRI-P0250",
  "work_id": "PKD-WRK-1981-VALISTRI",
  "title": "The VALIS Trilogy \u2014 Page 250",
  "segment_type": "page",
  "position": 250,
  "page_start": 250,
  "page_end": 250,
  "raw_text": "7\nCARDINAL FULTON STATLER Harms, Chief Prelate of the vast organizational\nnetwork that comprised the Christian-Islamic Church, could not for the life of\nhim figure out why there wasn\u2019t a sufficient amount of money in his Special\nDiscretionary Fund to cover his mistress\u2019s expenses.\nPerhaps, he pondered as his barber shaved him slowly and carefully, he had\ntoo dim a notion of the extent of Deirdre\u2019s needs.\nOriginally she had approached him\u2014no small task in itself, since it\ninvolved ascending the C.I.C. hierarchy rung by rung\u2014ascending without\nfalling entirely off before reaching the top. Deirdre, at that time, represented\nthe W.C.L.F., the World Civil Liberties Forum, and she had a list of abuses\u2014\nit was hazy to him then and it was still hazy to him, but anyhow the two of\nthem had wound up in bed, and now, officially, Dierdre had become his\nexecutive secretary.\nFor her work she blotted up two salaries: the visible one that came with her\njob and the invisible one doled out from the substantial account that he was\nfree to dispense as he saw fit. Where all this money went after it reached\nDeirdre he hadn\u2019t the foggiest idea. Bookkeeping had never been his strong\nsuit.\n\u201cYou want the yellow removed from this gray on the side, don\u2019t you?\u201d his\nbarber said, shaking up the contents of a bottle.\n\u201cPlease,\u201d Harms said; he nodded.\n\u201cYou think the Lakers are going to snap their losing streak?\u201d his barber said.\n\u201cI mean, they acquired that What\u2019s-his-name; he\u2019s nine feet two inches. If\nthey hadn\u2019t raised the\u2014\u201d\nTapping his ear, Harms said, \u201cI\u2019m listening to the news, Arnold.\u201d\n\u201cWell, yeah, I can see that, Father,\u201d Arnold the barber said as he splashed\nbleach onto the Chief Prelate\u2019s graying hair. \u201cBut there\u2019s something I wanted\nto ask you, about homosexual priests. Doesn\u2019t the Bible forbid\nhomosexuality? So I don\u2019t see how a priest can be a practicing homosexual.\u201d\nThe news that Harms was attempting to hear had to do with the health of the\nProcurator Maximus of the Scientific Legate, Nicholas Bulkowsky. A solemn\nprayer vigil had been formally called into being but nonetheless Bulkowsky\ncontinued to decline. Harms had, sub rosa, dispatched his personal physician\nto join the team of specialists attending to the Procurator\u2019s urgent condition.\nBulkowsky, as not only Cardinal Harms but the entire curia knew, was a\ndevout Christian. He had been converted by the evangelical, charismatic Dr.\nColin Passim who, at his revival meetings, often flew through the air in\ndramatic demonstration of the power of the Holy Spirit within him.\nOf course, Dr. Passim had not been the same since he sailed through a vast\n",
  "word_count": 444,
  "work_title": "The VALIS Trilogy",
  "work_slug": "the-valis-trilogy",
  "prev_seg_id": "PKD-SEG-VALISTRI-P0249",
  "next_seg_id": "PKD-SEG-VALISTRI-P0251"
}