{
  "topic_id": "PKD-MET-AWARENESS",
  "canonical_name": "awareness",
  "slug": "awareness",
  "topic_family": "metaphysics",
  "topic_subfamily": "consciousness",
  "definition": null,
  "pkd_relevance": null,
  "status": "provisional",
  "match_count": 76,
  "aliases": [],
  "matched_works": [
    {
      "work_id": "PKD-WRK-1974-EXEGESIS",
      "title": "The Exegesis of Philip K. Dick",
      "slug": "the-exegesis-of-philip-k-dick",
      "year_published": 1974,
      "relevance": "central",
      "match_count": 62
    },
    {
      "work_id": "PKD-WRK-1969-UBIK",
      "title": "Ubik",
      "slug": "ubik",
      "year_published": 1969,
      "relevance": "mentioned",
      "match_count": 4
    },
    {
      "work_id": "PKD-WRK-1978-COSMCOSM",
      "title": "Cosmogony and Cosmology",
      "slug": "cosmogony-and-cosmology",
      "year_published": 1978,
      "relevance": "significant",
      "match_count": 4
    },
    {
      "work_id": "PKD-WRK-1981-VALISTRI",
      "title": "The VALIS Trilogy",
      "slug": "the-valis-trilogy",
      "year_published": 1981,
      "relevance": "mentioned",
      "match_count": 3
    },
    {
      "work_id": "PKD-WRK-1965-5NOVELS",
      "title": "Five Great Novels (incl. Three Stigmata)",
      "slug": "five-great-novels-incl-three-stigmata",
      "year_published": 1965,
      "relevance": "mentioned",
      "match_count": 2
    },
    {
      "work_id": "PKD-WRK-1978-BUILDUNIVERSE",
      "title": "How to Build a Universe That Doesn't Fall Apart Two Days Later",
      "slug": "how-to-build-a-universe-that-doesnt-fall-apart-two-days-later",
      "year_published": 1978,
      "relevance": "peripheral",
      "match_count": 1
    }
  ],
  "matched_segments": [
    {
      "seg_id": "PKD-SEG-5NOVELS-P0123",
      "match_type": "exact_text",
      "matched_text": "awareness",
      "context_window": " urgent, professional-type, calm voice into the phone,\na voice deadly with awareness of peril and gravity and the\nrunning out of time. \"Either that or...",
      "seg_title": "Five Great Novels (incl. Three Stigmata) \u2014 Page 123",
      "segment_type": "page",
      "position": 123,
      "page_start": 123,
      "page_end": 123,
      "work_title": "Five Great Novels (incl. Three Stigmata)",
      "work_slug": "five-great-novels-incl-three-stigmata",
      "work_id": "PKD-WRK-1965-5NOVELS"
    },
    {
      "seg_id": "PKD-SEG-5NOVELS-P0191",
      "match_type": "exact_text",
      "matched_text": "awareness",
      "context_window": "patial\nrelationships in the room shifted; the alteration affected even\nhis awareness of time. \"It's in the . . .\" He yawned.\n\"You don't remember.\"\n\"I remember...",
      "seg_title": "Five Great Novels (incl. Three Stigmata) \u2014 Page 191",
      "segment_type": "page",
      "position": 191,
      "page_start": 191,
      "page_end": 191,
      "work_title": "Five Great Novels (incl. Three Stigmata)",
      "work_slug": "five-great-novels-incl-three-stigmata",
      "work_id": "PKD-WRK-1965-5NOVELS"
    },
    {
      "seg_id": "PKD-SEG-UBIK-P0115",
      "match_type": "exact_text",
      "matched_text": "awareness",
      "context_window": " hundred years ago at least. Obsessively, the term \nremained lodged within awareness; he could not forget it. \n     \u201cHow come you know that?\u201d the shop foreman...",
      "seg_title": "Ubik \u2014 Page 115",
      "segment_type": "page",
      "position": 115,
      "page_start": 115,
      "page_end": 115,
      "work_title": "Ubik",
      "work_slug": "ubik",
      "work_id": "PKD-WRK-1969-UBIK"
    },
    {
      "seg_id": "PKD-SEG-UBIK-P0164",
      "match_type": "exact_text",
      "matched_text": "Awareness",
      "context_window": "... \nabsolutely right.\u201d He looked startled and, then, acutely \nresponsive. Awareness glittered in his face. Of an unhappy, \nstricken kind. \n     \u201cI don\u2019t...",
      "seg_title": "Ubik \u2014 Page 164",
      "segment_type": "page",
      "position": 164,
      "page_start": 164,
      "page_end": 164,
      "work_title": "Ubik",
      "work_slug": "ubik",
      "work_id": "PKD-WRK-1969-UBIK"
    },
    {
      "seg_id": "PKD-SEG-UBIK-P0205",
      "match_type": "exact_text",
      "matched_text": "awareness",
      "context_window": " the present. I almost succeeded. There \nwas something in knowing that, an awareness of his own \ngreat strength. His final transcendental attempt. \n     The...",
      "seg_title": "Ubik \u2014 Page 205",
      "segment_type": "page",
      "position": 205,
      "page_start": 205,
      "page_end": 205,
      "work_title": "Ubik",
      "work_slug": "ubik",
      "work_id": "PKD-WRK-1969-UBIK"
    },
    {
      "seg_id": "PKD-SEG-UBIK-P0206",
      "match_type": "exact_text",
      "matched_text": "awareness",
      "context_window": "a synthetic ostrich-leather coat. He looked up at her, jarred \ninto awareness. \u201cMr. Chip?\u201d she said. Pretty and slender, \ndressed in hat, gloves, suit...",
      "seg_title": "Ubik \u2014 Page 206",
      "segment_type": "page",
      "position": 206,
      "page_start": 206,
      "page_end": 206,
      "work_title": "Ubik",
      "work_slug": "ubik",
      "work_id": "PKD-WRK-1969-UBIK"
    },
    {
      "seg_id": "PKD-SEG-EXEGESIS-P0028",
      "match_type": "exact_text",
      "matched_text": "awareness",
      "context_window": " caused changes in me; that is one\nenormous miracle ... but the heightened awareness caused me to see a\ndifferent universe: one which contained the red and...",
      "seg_title": "The Exegesis of Philip K. Dick \u2014 Page 28",
      "segment_type": "page",
      "position": 28,
      "page_start": 28,
      "page_end": 28,
      "work_title": "The Exegesis of Philip K. Dick",
      "work_slug": "the-exegesis-of-philip-k-dick",
      "work_id": "PKD-WRK-1974-EXEGESIS"
    },
    {
      "seg_id": "PKD-SEG-EXEGESIS-P0031",
      "match_type": "exact_text",
      "matched_text": "awareness",
      "context_window": "... to us all but I managed consciously to transduce above the threshold\nof awareness, which is unusual but not unique, and became aware of this\nconstant...",
      "seg_title": "The Exegesis of Philip K. Dick \u2014 Page 31",
      "segment_type": "page",
      "position": 31,
      "page_start": 31,
      "page_end": 31,
      "work_title": "The Exegesis of Philip K. Dick",
      "work_slug": "the-exegesis-of-philip-k-dick",
      "work_id": "PKD-WRK-1974-EXEGESIS"
    },
    {
      "seg_id": "PKD-SEG-EXEGESIS-P0032",
      "match_type": "exact_text",
      "matched_text": "awareness",
      "context_window": "... so to speak, with information about itself, thus giving\nus a certain awareness of itself. I would think that for purely fictional\npurposes the...",
      "seg_title": "The Exegesis of Philip K. Dick \u2014 Page 32",
      "segment_type": "page",
      "position": 32,
      "page_start": 32,
      "page_end": 32,
      "work_title": "The Exegesis of Philip K. Dick",
      "work_slug": "the-exegesis-of-philip-k-dick",
      "work_id": "PKD-WRK-1974-EXEGESIS"
    },
    {
      "seg_id": "PKD-SEG-EXEGESIS-P0056",
      "match_type": "exact_text",
      "matched_text": "awareness",
      "context_window": "... and was gone; I floundered in the void, suffering. I think\nthis was an awareness that for all its value, this new worldview being\ndominant in me and...",
      "seg_title": "The Exegesis of Philip K. Dick \u2014 Page 56",
      "segment_type": "page",
      "position": 56,
      "page_start": 56,
      "page_end": 56,
      "work_title": "The Exegesis of Philip K. Dick",
      "work_slug": "the-exegesis-of-philip-k-dick",
      "work_id": "PKD-WRK-1974-EXEGESIS"
    },
    {
      "seg_id": "PKD-SEG-EXEGESIS-P0086",
      "match_type": "exact_text",
      "matched_text": "awareness",
      "context_window": "... come out of my mind, my mental processes; it wasn't a concept or even\nan awareness internally: I perceived it. I saw it. I pierced the veil, so to...",
      "seg_title": "The Exegesis of Philip K. Dick \u2014 Page 86",
      "segment_type": "page",
      "position": 86,
      "page_start": 86,
      "page_end": 86,
      "work_title": "The Exegesis of Philip K. Dick",
      "work_slug": "the-exegesis-of-philip-k-dick",
      "work_id": "PKD-WRK-1974-EXEGESIS"
    },
    {
      "seg_id": "PKD-SEG-EXEGESIS-P0088",
      "match_type": "exact_text",
      "matched_text": "awareness",
      "context_window": "... of God, the Perfect Kingdom, floods back into being: back into\nawareness of itself, that it is Here; and it is here Now.\nIt contains within it...",
      "seg_title": "The Exegesis of Philip K. Dick \u2014 Page 88",
      "segment_type": "page",
      "position": 88,
      "page_start": 88,
      "page_end": 88,
      "work_title": "The Exegesis of Philip K. Dick",
      "work_slug": "the-exegesis-of-philip-k-dick",
      "work_id": "PKD-WRK-1974-EXEGESIS"
    },
    {
      "seg_id": "PKD-SEG-EXEGESIS-P0093",
      "match_type": "exact_text",
      "matched_text": "awareness",
      "context_window": "... collectively generated\ntheir \"reality\" outside their field of conscious awareness. (At night, in sleep,\nthis mental mechanism dims, and other elements...",
      "seg_title": "The Exegesis of Philip K. Dick \u2014 Page 93",
      "segment_type": "page",
      "position": 93,
      "page_start": 93,
      "page_end": 93,
      "work_title": "The Exegesis of Philip K. Dick",
      "work_slug": "the-exegesis-of-philip-k-dick",
      "work_id": "PKD-WRK-1974-EXEGESIS"
    },
    {
      "seg_id": "PKD-SEG-EXEGESIS-P0110",
      "match_type": "exact_text",
      "matched_text": "awareness",
      "context_window": "... manifold retentions of prior impressions\noutside the field of conscious awareness; i.e., although he doesn't \"remember\"\nin the ego-sense, his entire...",
      "seg_title": "The Exegesis of Philip K. Dick \u2014 Page 110",
      "segment_type": "page",
      "position": 110,
      "page_start": 110,
      "page_end": 110,
      "work_title": "The Exegesis of Philip K. Dick",
      "work_slug": "the-exegesis-of-philip-k-dick",
      "work_id": "PKD-WRK-1974-EXEGESIS"
    },
    {
      "seg_id": "PKD-SEG-EXEGESIS-P0136",
      "match_type": "exact_text",
      "matched_text": "awareness",
      "context_window": " a moral tone to life (\"overthrow the tyranny\"). I saw, too, that\nesthetic awareness of music and art was my outlet my saving outlet; I really\ndidn't see the...",
      "seg_title": "The Exegesis of Philip K. Dick \u2014 Page 136",
      "segment_type": "page",
      "position": 136,
      "page_start": 136,
      "page_end": 136,
      "work_title": "The Exegesis of Philip K. Dick",
      "work_slug": "the-exegesis-of-philip-k-dick",
      "work_id": "PKD-WRK-1974-EXEGESIS"
    },
    {
      "seg_id": "PKD-SEG-EXEGESIS-P0149",
      "match_type": "exact_text",
      "matched_text": "awareness",
      "context_window": "... order to release changes in me. Time, properly understood, is merely an\nawareness of the procession of these little, weak cueing signs, their advance\nas we...",
      "seg_title": "The Exegesis of Philip K. Dick \u2014 Page 149",
      "segment_type": "page",
      "position": 149,
      "page_start": 149,
      "page_end": 149,
      "work_title": "The Exegesis of Philip K. Dick",
      "work_slug": "the-exegesis-of-philip-k-dick",
      "work_id": "PKD-WRK-1974-EXEGESIS"
    },
    {
      "seg_id": "PKD-SEG-EXEGESIS-P0168",
      "match_type": "exact_text",
      "matched_text": "awareness",
      "context_window": " Plan; thus we who were\nsecular scientific and left wing came around to an awareness of the Logos,\nand, as Heraclitus says, \"we woke up from our dream and...",
      "seg_title": "The Exegesis of Philip K. Dick \u2014 Page 168",
      "segment_type": "page",
      "position": 168,
      "page_start": 168,
      "page_end": 168,
      "work_title": "The Exegesis of Philip K. Dick",
      "work_slug": "the-exegesis-of-philip-k-dick",
      "work_id": "PKD-WRK-1974-EXEGESIS"
    },
    {
      "seg_id": "PKD-SEG-EXEGESIS-P0176",
      "match_type": "exact_text",
      "matched_text": "awareness",
      "context_window": "... externally in terms of\ntransformation ratifies what I knew from an inner awareness to be the case;\nthe two fit perfectly. What was Rome of that period...",
      "seg_title": "The Exegesis of Philip K. Dick \u2014 Page 176",
      "segment_type": "page",
      "position": 176,
      "page_start": 176,
      "page_end": 176,
      "work_title": "The Exegesis of Philip K. Dick",
      "work_slug": "the-exegesis-of-philip-k-dick",
      "work_id": "PKD-WRK-1974-EXEGESIS"
    },
    {
      "seg_id": "PKD-SEG-EXEGESIS-P0181",
      "match_type": "exact_text",
      "matched_text": "awareness",
      "context_window": " it. I am sure of what I saw. Maybe by \"possessed\" it should always read,\n\"awareness of being possessed,\" implying we are (the environment outside,\neach of us...",
      "seg_title": "The Exegesis of Philip K. Dick \u2014 Page 181",
      "segment_type": "page",
      "position": 181,
      "page_start": 181,
      "page_end": 181,
      "work_title": "The Exegesis of Philip K. Dick",
      "work_slug": "the-exegesis-of-philip-k-dick",
      "work_id": "PKD-WRK-1974-EXEGESIS"
    },
    {
      "seg_id": "PKD-SEG-EXEGESIS-P0182",
      "match_type": "exact_text",
      "matched_text": "awareness",
      "context_window": "... to our \"consciousness,\" or a rise in level of intention and\nawareness, of purpose (locally, I guess). [...]\nI am lying in bed here and I am...",
      "seg_title": "The Exegesis of Philip K. Dick \u2014 Page 182",
      "segment_type": "page",
      "position": 182,
      "page_start": 182,
      "page_end": 182,
      "work_title": "The Exegesis of Philip K. Dick",
      "work_slug": "the-exegesis-of-philip-k-dick",
      "work_id": "PKD-WRK-1974-EXEGESIS"
    },
    {
      "seg_id": "PKD-SEG-EXEGESIS-P0191",
      "match_type": "exact_text",
      "matched_text": "awareness",
      "context_window": "us, to arouse us to conscious awareness. We, as a portion of it, have fallen\nasleep somehow. All metaphors...",
      "seg_title": "The Exegesis of Philip K. Dick \u2014 Page 191",
      "segment_type": "page",
      "position": 191,
      "page_start": 191,
      "page_end": 191,
      "work_title": "The Exegesis of Philip K. Dick",
      "work_slug": "the-exegesis-of-philip-k-dick",
      "work_id": "PKD-WRK-1974-EXEGESIS"
    },
    {
      "seg_id": "PKD-SEG-EXEGESIS-P0193",
      "match_type": "exact_text",
      "matched_text": "awareness",
      "context_window": "... which must be based, for obvious reasons, on a\nperceptual and cognitive awareness that He is actually present.\nSo what I've done (supra) is change the...",
      "seg_title": "The Exegesis of Philip K. Dick \u2014 Page 193",
      "segment_type": "page",
      "position": 193,
      "page_start": 193,
      "page_end": 193,
      "work_title": "The Exegesis of Philip K. Dick",
      "work_slug": "the-exegesis-of-philip-k-dick",
      "work_id": "PKD-WRK-1974-EXEGESIS"
    },
    {
      "seg_id": "PKD-SEG-EXEGESIS-P0205",
      "match_type": "exact_text",
      "matched_text": "awareness",
      "context_window": "... is an actual evil, not\nmerely a view-point evil. It is basically self-awareness: self as part of this and\nnow disclosed (to a higher eye). It is the...",
      "seg_title": "The Exegesis of Philip K. Dick \u2014 Page 205",
      "segment_type": "page",
      "position": 205,
      "page_start": 205,
      "page_end": 205,
      "work_title": "The Exegesis of Philip K. Dick",
      "work_slug": "the-exegesis-of-philip-k-dick",
      "work_id": "PKD-WRK-1974-EXEGESIS"
    },
    {
      "seg_id": "PKD-SEG-EXEGESIS-P0212",
      "match_type": "exact_text",
      "matched_text": "awareness",
      "context_window": "... That is, put\npsychologically, I could not continue to thrust outside of awareness these\nextraordinary items in my books and in my life, but had to face...",
      "seg_title": "The Exegesis of Philip K. Dick \u2014 Page 212",
      "segment_type": "page",
      "position": 212,
      "page_start": 212,
      "page_end": 212,
      "work_title": "The Exegesis of Philip K. Dick",
      "work_slug": "the-exegesis-of-philip-k-dick",
      "work_id": "PKD-WRK-1974-EXEGESIS"
    },
    {
      "seg_id": "PKD-SEG-EXEGESIS-P0213",
      "match_type": "exact_text",
      "matched_text": "awareness",
      "context_window": " legitimate and real and I should hang onto it (I am).\nEqually real was my awareness of fighting off an absolutely evil enemy intent\non zapping me once and...",
      "seg_title": "The Exegesis of Philip K. Dick \u2014 Page 213",
      "segment_type": "page",
      "position": 213,
      "page_start": 213,
      "page_end": 213,
      "work_title": "The Exegesis of Philip K. Dick",
      "work_slug": "the-exegesis-of-philip-k-dick",
      "work_id": "PKD-WRK-1974-EXEGESIS"
    },
    {
      "seg_id": "PKD-SEG-EXEGESIS-P0240",
      "match_type": "exact_text",
      "matched_text": "awareness",
      "context_window": "... merely a next stage in moving from\nplace to place, but the recovery of awareness of identity as one of\nthe \"bees\" or constituents of the...",
      "seg_title": "The Exegesis of Philip K. Dick \u2014 Page 240",
      "segment_type": "page",
      "position": 240,
      "page_start": 240,
      "page_end": 240,
      "work_title": "The Exegesis of Philip K. Dick",
      "work_slug": "the-exegesis-of-philip-k-dick",
      "work_id": "PKD-WRK-1974-EXEGESIS"
    },
    {
      "seg_id": "PKD-SEG-EXEGESIS-P0241",
      "match_type": "exact_text",
      "matched_text": "Awareness",
      "context_window": "... of bees: a\ncolony of bees is a collective intelligence, par excellence. Awareness of the\nliving universe creature and one's identity in it as one \"bee\" is...",
      "seg_title": "The Exegesis of Philip K. Dick \u2014 Page 241",
      "segment_type": "page",
      "position": 241,
      "page_start": 241,
      "page_end": 241,
      "work_title": "The Exegesis of Philip K. Dick",
      "work_slug": "the-exegesis-of-philip-k-dick",
      "work_id": "PKD-WRK-1974-EXEGESIS"
    },
    {
      "seg_id": "PKD-SEG-EXEGESIS-P0248",
      "match_type": "exact_text",
      "matched_text": "awareness",
      "context_window": "... although outwardly all seems to be as it\nhas always been. Hence my inner awareness that contrary to everything I\nbelieve possible, myself, my \"me\" was...",
      "seg_title": "The Exegesis of Philip K. Dick \u2014 Page 248",
      "segment_type": "page",
      "position": 248,
      "page_start": 248,
      "page_end": 248,
      "work_title": "The Exegesis of Philip K. Dick",
      "work_slug": "the-exegesis-of-philip-k-dick",
      "work_id": "PKD-WRK-1974-EXEGESIS"
    },
    {
      "seg_id": "PKD-SEG-EXEGESIS-P0266",
      "match_type": "exact_text",
      "matched_text": "awareness",
      "context_window": "... a sense of purpose. Of\npersonal worth\u2014and above all meaning, from my awareness of God.\n",
      "seg_title": "The Exegesis of Philip K. Dick \u2014 Page 266",
      "segment_type": "page",
      "position": 266,
      "page_start": 266,
      "page_end": 266,
      "work_title": "The Exegesis of Philip K. Dick",
      "work_slug": "the-exegesis-of-philip-k-dick",
      "work_id": "PKD-WRK-1974-EXEGESIS"
    },
    {
      "seg_id": "PKD-SEG-EXEGESIS-P0274",
      "match_type": "exact_text",
      "matched_text": "awareness",
      "context_window": "... and 1000 B.C. Why Jaynes' \"best guess: man was somehow jolted into\nawareness (!) by social chaos. Vast migration, invasion and natural\ncatastrophes...",
      "seg_title": "The Exegesis of Philip K. Dick \u2014 Page 274",
      "segment_type": "page",
      "position": 274,
      "page_start": 274,
      "page_end": 274,
      "work_title": "The Exegesis of Philip K. Dick",
      "work_slug": "the-exegesis-of-philip-k-dick",
      "work_id": "PKD-WRK-1974-EXEGESIS"
    },
    {
      "seg_id": "PKD-SEG-EXEGESIS-P0278",
      "match_type": "exact_text",
      "matched_text": "awareness",
      "context_window": "... this is by a continually growing\ndevelopment and transfer of knowing (awareness), by means of transferred\ninformation throughout the interstices or...",
      "seg_title": "The Exegesis of Philip K. Dick \u2014 Page 278",
      "segment_type": "page",
      "position": 278,
      "page_start": 278,
      "page_end": 278,
      "work_title": "The Exegesis of Philip K. Dick",
      "work_slug": "the-exegesis-of-philip-k-dick",
      "work_id": "PKD-WRK-1974-EXEGESIS"
    },
    {
      "seg_id": "PKD-SEG-EXEGESIS-P0305",
      "match_type": "exact_text",
      "matched_text": "awareness",
      "context_window": "... 2-74 when I saw the\nGolden Fish; in a single moment of total knowledge (awareness of the true\nstate of things) I withdrew my belief in what I customarily...",
      "seg_title": "The Exegesis of Philip K. Dick \u2014 Page 305",
      "segment_type": "page",
      "position": 305,
      "page_start": 305,
      "page_end": 305,
      "work_title": "The Exegesis of Philip K. Dick",
      "work_slug": "the-exegesis-of-philip-k-dick",
      "work_id": "PKD-WRK-1974-EXEGESIS"
    },
    {
      "seg_id": "PKD-SEG-EXEGESIS-P0319",
      "match_type": "exact_text",
      "matched_text": "awareness",
      "context_window": "... \na \n(mere) \nholographic \nprojection. \nWithout \nthe\nunderstanding and awareness of the real (ultimate) reality being one of mind,\nthe concept \"the word\"...",
      "seg_title": "The Exegesis of Philip K. Dick \u2014 Page 319",
      "segment_type": "page",
      "position": 319,
      "page_start": 319,
      "page_end": 319,
      "work_title": "The Exegesis of Philip K. Dick",
      "work_slug": "the-exegesis-of-philip-k-dick",
      "work_id": "PKD-WRK-1974-EXEGESIS"
    },
    {
      "seg_id": "PKD-SEG-EXEGESIS-P0323",
      "match_type": "exact_text",
      "matched_text": "awareness",
      "context_window": "... time is the true receptacle of being (for the organism)\nanamnesis equals awareness of the organism as such: a seeing of the more or\nless complete entelechy;...",
      "seg_title": "The Exegesis of Philip K. Dick \u2014 Page 323",
      "segment_type": "page",
      "position": 323,
      "page_start": 323,
      "page_end": 323,
      "work_title": "The Exegesis of Philip K. Dick",
      "work_slug": "the-exegesis-of-philip-k-dick",
      "work_id": "PKD-WRK-1974-EXEGESIS"
    },
    {
      "seg_id": "PKD-SEG-EXEGESIS-P0324",
      "match_type": "exact_text",
      "matched_text": "awareness",
      "context_window": "... and relentlessly; that is their\nfates. What Christ offers is miraculous awareness of and hence participation\nin (with joy)\u2014the totality; to be united with...",
      "seg_title": "The Exegesis of Philip K. Dick \u2014 Page 324",
      "segment_type": "page",
      "position": 324,
      "page_start": 324,
      "page_end": 324,
      "work_title": "The Exegesis of Philip K. Dick",
      "work_slug": "the-exegesis-of-philip-k-dick",
      "work_id": "PKD-WRK-1974-EXEGESIS"
    },
    {
      "seg_id": "PKD-SEG-EXEGESIS-P0340",
      "match_type": "exact_text",
      "matched_text": "awareness",
      "context_window": " by section it is returning to (or achieving finally) consciousness: hence\nawareness of its true condition. When Christ left, the organism fell asleep....",
      "seg_title": "The Exegesis of Philip K. Dick \u2014 Page 340",
      "segment_type": "page",
      "position": 340,
      "page_start": 340,
      "page_end": 340,
      "work_title": "The Exegesis of Philip K. Dick",
      "work_slug": "the-exegesis-of-philip-k-dick",
      "work_id": "PKD-WRK-1974-EXEGESIS"
    },
    {
      "seg_id": "PKD-SEG-EXEGESIS-P0353",
      "match_type": "exact_text",
      "matched_text": "awareness",
      "context_window": "... 3\u2014but is, finally, a mere illusion\u2014\nstage 6).\n \n[14:63] The awareness of sorrow is the first step in the encountering of God,\nas is laughter....",
      "seg_title": "The Exegesis of Philip K. Dick \u2014 Page 353",
      "segment_type": "page",
      "position": 353,
      "page_start": 353,
      "page_end": 353,
      "work_title": "The Exegesis of Philip K. Dick",
      "work_slug": "the-exegesis-of-philip-k-dick",
      "work_id": "PKD-WRK-1974-EXEGESIS"
    },
    {
      "seg_id": "PKD-SEG-EXEGESIS-P0367",
      "match_type": "exact_text",
      "matched_text": "awareness",
      "context_window": "... act\u2014the crucial act of balking was, for me, moral. It\ndevelops out of an awareness of the counterfeit: viz: \"it is wrong ethically to\ncollude with the...",
      "seg_title": "The Exegesis of Philip K. Dick \u2014 Page 367",
      "segment_type": "page",
      "position": 367,
      "page_start": 367,
      "page_end": 367,
      "work_title": "The Exegesis of Philip K. Dick",
      "work_slug": "the-exegesis-of-philip-k-dick",
      "work_id": "PKD-WRK-1974-EXEGESIS"
    },
    {
      "seg_id": "PKD-SEG-EXEGESIS-P0381",
      "match_type": "exact_text",
      "matched_text": "awareness",
      "context_window": " evolution/revolution. The brain\nincited this advance in consciousness and awareness. Just to examine what\nwas overthrown is to miss the point. I am\u2014have...",
      "seg_title": "The Exegesis of Philip K. Dick \u2014 Page 381",
      "segment_type": "page",
      "position": 381,
      "page_start": 381,
      "page_end": 381,
      "work_title": "The Exegesis of Philip K. Dick",
      "work_slug": "the-exegesis-of-philip-k-dick",
      "work_id": "PKD-WRK-1974-EXEGESIS"
    },
    {
      "seg_id": "PKD-SEG-EXEGESIS-P0457",
      "match_type": "exact_text",
      "matched_text": "awareness",
      "context_window": "... otherwise it never goes away.\nDespite what our senses report, somehow awareness (enlightenment) is\n",
      "seg_title": "The Exegesis of Philip K. Dick \u2014 Page 457",
      "segment_type": "page",
      "position": 457,
      "page_start": 457,
      "page_end": 457,
      "work_title": "The Exegesis of Philip K. Dick",
      "work_slug": "the-exegesis-of-philip-k-dick",
      "work_id": "PKD-WRK-1974-EXEGESIS"
    },
    {
      "seg_id": "PKD-SEG-EXEGESIS-P0470",
      "match_type": "exact_text",
      "matched_text": "awareness",
      "context_window": "... completed and,\nsimultaneously, macrocosm completed, both in terms of my awareness, inner\n[micro or Atman] and outer [macro or Brahman].)\nThere was nothing...",
      "seg_title": "The Exegesis of Philip K. Dick \u2014 Page 470",
      "segment_type": "page",
      "position": 470,
      "page_start": 470,
      "page_end": 470,
      "work_title": "The Exegesis of Philip K. Dick",
      "work_slug": "the-exegesis-of-philip-k-dick",
      "work_id": "PKD-WRK-1974-EXEGESIS"
    },
    {
      "seg_id": "PKD-SEG-EXEGESIS-P0525",
      "match_type": "exact_text",
      "matched_text": "awareness",
      "context_window": "... that is guessed at. What\nis central is the balance between an intense awareness of pain or evil, which is\nclearly revealed, and an intuitive apprehension...",
      "seg_title": "The Exegesis of Philip K. Dick \u2014 Page 525",
      "segment_type": "page",
      "position": 525,
      "page_start": 525,
      "page_end": 525,
      "work_title": "The Exegesis of Philip K. Dick",
      "work_slug": "the-exegesis-of-philip-k-dick",
      "work_id": "PKD-WRK-1974-EXEGESIS"
    },
    {
      "seg_id": "PKD-SEG-EXEGESIS-P0526",
      "match_type": "exact_text",
      "matched_text": "awareness",
      "context_window": "... my response to my direct knowledge and\nexperience of Valis, of my awareness of its authority over the irrational\u2014\nwhich I identify with \"astral...",
      "seg_title": "The Exegesis of Philip K. Dick \u2014 Page 526",
      "segment_type": "page",
      "position": 526,
      "page_start": 526,
      "page_end": 526,
      "work_title": "The Exegesis of Philip K. Dick",
      "work_slug": "the-exegesis-of-philip-k-dick",
      "work_id": "PKD-WRK-1974-EXEGESIS"
    },
    {
      "seg_id": "PKD-SEG-EXEGESIS-P0577",
      "match_type": "exact_text",
      "matched_text": "awareness",
      "context_window": "... faith in YHWH is required. Here is where primal angst enters:\nawareness (v. VR) comes in, awareness of what losing would mean (BIP).\nWorse\u2014no...",
      "seg_title": "The Exegesis of Philip K. Dick \u2014 Page 577",
      "segment_type": "page",
      "position": 577,
      "page_start": 577,
      "page_end": 577,
      "work_title": "The Exegesis of Philip K. Dick",
      "work_slug": "the-exegesis-of-philip-k-dick",
      "work_id": "PKD-WRK-1974-EXEGESIS"
    },
    {
      "seg_id": "PKD-SEG-EXEGESIS-P0593",
      "match_type": "exact_text",
      "matched_text": "awareness",
      "context_window": "... represents\nsuccessive levels of self-disclosure by YHWH\u2014meaning self-awareness.\nHuman history is the deity waking up. The opponent to YHWH at any\nmoment...",
      "seg_title": "The Exegesis of Philip K. Dick \u2014 Page 593",
      "segment_type": "page",
      "position": 593,
      "page_start": 593,
      "page_end": 593,
      "work_title": "The Exegesis of Philip K. Dick",
      "work_slug": "the-exegesis-of-philip-k-dick",
      "work_id": "PKD-WRK-1974-EXEGESIS"
    },
    {
      "seg_id": "PKD-SEG-EXEGESIS-P0599",
      "match_type": "exact_text",
      "matched_text": "awareness",
      "context_window": "... to be, derived from the suffering sheep. And I say in anguish and\nawareness of the sheep's anguish, \"I hope they (the torturers of the sheep)\nburn in...",
      "seg_title": "The Exegesis of Philip K. Dick \u2014 Page 599",
      "segment_type": "page",
      "position": 599,
      "page_start": 599,
      "page_end": 599,
      "work_title": "The Exegesis of Philip K. Dick",
      "work_slug": "the-exegesis-of-philip-k-dick",
      "work_id": "PKD-WRK-1974-EXEGESIS"
    },
    {
      "seg_id": "PKD-SEG-EXEGESIS-P0602",
      "match_type": "exact_text",
      "matched_text": "awareness",
      "context_window": "... down throughout creation! (v. Taoism!)\nIn terms of the evolution of awareness, the total system advances through\nstages\u278a until it becomes aware of the...",
      "seg_title": "The Exegesis of Philip K. Dick \u2014 Page 602",
      "segment_type": "page",
      "position": 602,
      "page_start": 602,
      "page_end": 602,
      "work_title": "The Exegesis of Philip K. Dick",
      "work_slug": "the-exegesis-of-philip-k-dick",
      "work_id": "PKD-WRK-1974-EXEGESIS"
    },
    {
      "seg_id": "PKD-SEG-EXEGESIS-P0634",
      "match_type": "exact_text",
      "matched_text": "awareness",
      "context_window": "... not exist, but is\nbrought into existence parallel with the percipient's awareness of it, this\nhaving to do with the participant-observer of quantum...",
      "seg_title": "The Exegesis of Philip K. Dick \u2014 Page 634",
      "segment_type": "page",
      "position": 634,
      "page_start": 634,
      "page_end": 634,
      "work_title": "The Exegesis of Philip K. Dick",
      "work_slug": "the-exegesis-of-philip-k-dick",
      "work_id": "PKD-WRK-1974-EXEGESIS"
    },
    {
      "seg_id": "PKD-SEG-EXEGESIS-P0637",
      "match_type": "exact_text",
      "matched_text": "awareness",
      "context_window": "... the perception of it\u2014of\nnecessity from within itself, which is a self-awareness. Thus the percipient of\nValis and Valis are part of one field.\nThe flux...",
      "seg_title": "The Exegesis of Philip K. Dick \u2014 Page 637",
      "segment_type": "page",
      "position": 637,
      "page_start": 637,
      "page_end": 637,
      "work_title": "The Exegesis of Philip K. Dick",
      "work_slug": "the-exegesis-of-philip-k-dick",
      "work_id": "PKD-WRK-1974-EXEGESIS"
    },
    {
      "seg_id": "PKD-SEG-EXEGESIS-P0639",
      "match_type": "exact_text",
      "matched_text": "awareness",
      "context_window": "... leap in abstracting\nfrom accident to essence on my part, a perception/awareness of einai\nunderlying accidents as follows:\n\"Superimposition\" of the 2...",
      "seg_title": "The Exegesis of Philip K. Dick \u2014 Page 639",
      "segment_type": "page",
      "position": 639,
      "page_start": 639,
      "page_end": 639,
      "work_title": "The Exegesis of Philip K. Dick",
      "work_slug": "the-exegesis-of-philip-k-dick",
      "work_id": "PKD-WRK-1974-EXEGESIS"
    },
    {
      "seg_id": "PKD-SEG-EXEGESIS-P0655",
      "match_type": "exact_text",
      "matched_text": "awareness",
      "context_window": " of\nself-knowledge.) Perhaps this is the ultimate price of the game: self-\nawareness, acquired through \"external\" plural standpoints, of which I am one.\nThen...",
      "seg_title": "The Exegesis of Philip K. Dick \u2014 Page 655",
      "segment_type": "page",
      "position": 655,
      "page_start": 655,
      "page_end": 655,
      "work_title": "The Exegesis of Philip K. Dick",
      "work_slug": "the-exegesis-of-philip-k-dick",
      "work_id": "PKD-WRK-1974-EXEGESIS"
    },
    {
      "seg_id": "PKD-SEG-EXEGESIS-P0658",
      "match_type": "exact_text",
      "matched_text": "awareness",
      "context_window": "... having moved in time and space. The\ninternal arrangement was its own awareness of itself. Itself as map.\nAs incredible as it may seem, I actually didn't...",
      "seg_title": "The Exegesis of Philip K. Dick \u2014 Page 658",
      "segment_type": "page",
      "position": 658,
      "page_start": 658,
      "page_end": 658,
      "work_title": "The Exegesis of Philip K. Dick",
      "work_slug": "the-exegesis-of-philip-k-dick",
      "work_id": "PKD-WRK-1974-EXEGESIS"
    },
    {
      "seg_id": "PKD-SEG-EXEGESIS-P0674",
      "match_type": "exact_text",
      "matched_text": "awareness",
      "context_window": "... sense of evil, oppression and suffering\nwas undermined drastically by an awareness of divine goodness, love,\nwisdom and power (cf. my Charles Platt...",
      "seg_title": "The Exegesis of Philip K. Dick \u2014 Page 674",
      "segment_type": "page",
      "position": 674,
      "page_start": 674,
      "page_end": 674,
      "work_title": "The Exegesis of Philip K. Dick",
      "work_slug": "the-exegesis-of-philip-k-dick",
      "work_id": "PKD-WRK-1974-EXEGESIS"
    },
    {
      "seg_id": "PKD-SEG-EXEGESIS-P0707",
      "match_type": "exact_text",
      "matched_text": "awareness",
      "context_window": "... (spiritual and mental, especially) is the basis of my\nwriting, as is my awareness of the frailty of life and how easily it passes over\ninto death. Thus,...",
      "seg_title": "The Exegesis of Philip K. Dick \u2014 Page 707",
      "segment_type": "page",
      "position": 707,
      "page_start": 707,
      "page_end": 707,
      "work_title": "The Exegesis of Philip K. Dick",
      "work_slug": "the-exegesis-of-philip-k-dick",
      "work_id": "PKD-WRK-1974-EXEGESIS"
    },
    {
      "seg_id": "PKD-SEG-EXEGESIS-P0722",
      "match_type": "exact_text",
      "matched_text": "awareness",
      "context_window": "... processes, i.e., its thinking, and its nonbeing\nphase, lies outside our awareness. The initial false move that it tries out\nduring its zero phase is...",
      "seg_title": "The Exegesis of Philip K. Dick \u2014 Page 722",
      "segment_type": "page",
      "position": 722,
      "page_start": 722,
      "page_end": 722,
      "work_title": "The Exegesis of Philip K. Dick",
      "work_slug": "the-exegesis-of-philip-k-dick",
      "work_id": "PKD-WRK-1974-EXEGESIS"
    },
    {
      "seg_id": "PKD-SEG-EXEGESIS-P0760",
      "match_type": "exact_text",
      "matched_text": "awareness",
      "context_window": "... Moral, having to do with choice? Freedom? Autonomy?\nSelf awareness [e.g., clarity of idea of his goals/values]? How he ranks the\nworth of...",
      "seg_title": "The Exegesis of Philip K. Dick \u2014 Page 760",
      "segment_type": "page",
      "position": 760,
      "page_start": 760,
      "page_end": 760,
      "work_title": "The Exegesis of Philip K. Dick",
      "work_slug": "the-exegesis-of-philip-k-dick",
      "work_id": "PKD-WRK-1974-EXEGESIS"
    },
    {
      "seg_id": "PKD-SEG-EXEGESIS-P0765",
      "match_type": "exact_text",
      "matched_text": "awareness",
      "context_window": "... itself. The meta-\nabstraction was the coming into existence of pure self awareness, i.e., it (not\nme).\nI am saying that 2-3-74 was Anokhi, pure...",
      "seg_title": "The Exegesis of Philip K. Dick \u2014 Page 765",
      "segment_type": "page",
      "position": 765,
      "page_start": 765,
      "page_end": 765,
      "work_title": "The Exegesis of Philip K. Dick",
      "work_slug": "the-exegesis-of-philip-k-dick",
      "work_id": "PKD-WRK-1974-EXEGESIS"
    },
    {
      "seg_id": "PKD-SEG-EXEGESIS-P0769",
      "match_type": "exact_text",
      "matched_text": "awareness",
      "context_window": " What if creation (verb) was accidental? A byproduct of the\nGodhead's self-awareness expressed by it uttering the word (perhaps Anokhi\n\u2014?). Its self-awareness...",
      "seg_title": "The Exegesis of Philip K. Dick \u2014 Page 769",
      "segment_type": "page",
      "position": 769,
      "page_start": 769,
      "page_end": 769,
      "work_title": "The Exegesis of Philip K. Dick",
      "work_slug": "the-exegesis-of-philip-k-dick",
      "work_id": "PKD-WRK-1974-EXEGESIS"
    },
    {
      "seg_id": "PKD-SEG-EXEGESIS-P0791",
      "match_type": "exact_text",
      "matched_text": "awareness",
      "context_window": " conscience will always\naccuse you! Interjected authority transformed into awareness of guilt, which\nis to say falling short\u2014the literal meaning of...",
      "seg_title": "The Exegesis of Philip K. Dick \u2014 Page 791",
      "segment_type": "page",
      "position": 791,
      "page_start": 791,
      "page_end": 791,
      "work_title": "The Exegesis of Philip K. Dick",
      "work_slug": "the-exegesis-of-philip-k-dick",
      "work_id": "PKD-WRK-1974-EXEGESIS"
    },
    {
      "seg_id": "PKD-SEG-EXEGESIS-P0818",
      "match_type": "exact_text",
      "matched_text": "awareness",
      "context_window": "... divine essence\nitself. It is pure knowing. It is not an emotion; it is awareness of its own\nessence: two mirrors: sorrow and awareness of sorrow, its own...",
      "seg_title": "The Exegesis of Philip K. Dick \u2014 Page 818",
      "segment_type": "page",
      "position": 818,
      "page_start": 818,
      "page_end": 818,
      "work_title": "The Exegesis of Philip K. Dick",
      "work_slug": "the-exegesis-of-philip-k-dick",
      "work_id": "PKD-WRK-1974-EXEGESIS"
    },
    {
      "seg_id": "PKD-SEG-EXEGESIS-P0825",
      "match_type": "exact_text",
      "matched_text": "awareness",
      "context_window": "... testaments, and he was aware that it is a world; that is his\ncrucial awareness; this third entity, this spiritual meta-entity created\nby an accord...",
      "seg_title": "The Exegesis of Philip K. Dick \u2014 Page 825",
      "segment_type": "page",
      "position": 825,
      "page_start": 825,
      "page_end": 825,
      "work_title": "The Exegesis of Philip K. Dick",
      "work_slug": "the-exegesis-of-philip-k-dick",
      "work_id": "PKD-WRK-1974-EXEGESIS"
    },
    {
      "seg_id": "PKD-SEG-EXEGESIS-P0832",
      "match_type": "exact_text",
      "matched_text": "awareness",
      "context_window": "... and that the person is dependent on an outside source to\nrouse him to awareness of his state and to reverse that state. Upon it being\nreversed\u2014ontological",
      "seg_title": "The Exegesis of Philip K. Dick \u2014 Page 832",
      "segment_type": "page",
      "position": 832,
      "page_start": 832,
      "page_end": 832,
      "work_title": "The Exegesis of Philip K. Dick",
      "work_slug": "the-exegesis-of-philip-k-dick",
      "work_id": "PKD-WRK-1974-EXEGESIS"
    },
    {
      "seg_id": "PKD-SEG-EXEGESIS-P0843",
      "match_type": "exact_text",
      "matched_text": "awareness",
      "context_window": " come over\u2014I realized then that hell consisted of a state of\nabsolute self-awareness of what you had done\u2014forever; that is, you accused\nyourself and found...",
      "seg_title": "The Exegesis of Philip K. Dick \u2014 Page 843",
      "segment_type": "page",
      "position": 843,
      "page_start": 843,
      "page_end": 843,
      "work_title": "The Exegesis of Philip K. Dick",
      "work_slug": "the-exegesis-of-philip-k-dick",
      "work_id": "PKD-WRK-1974-EXEGESIS"
    },
    {
      "seg_id": "PKD-SEG-EXEGESIS-P0896",
      "match_type": "exact_text",
      "matched_text": "awareness",
      "context_window": "... \"the lethal damage done by the\ninquiring mind\" by the fact that\u2014and its awareness of the fact that (the\nsecond point is necessary!)\u2014it knows only itself...",
      "seg_title": "The Exegesis of Philip K. Dick \u2014 Page 896",
      "segment_type": "page",
      "position": 896,
      "page_start": 896,
      "page_end": 896,
      "work_title": "The Exegesis of Philip K. Dick",
      "work_slug": "the-exegesis-of-philip-k-dick",
      "work_id": "PKD-WRK-1974-EXEGESIS"
    },
    {
      "seg_id": "PKD-SEG-EXEGESIS-P0931",
      "match_type": "exact_text",
      "matched_text": "awareness",
      "context_window": "... [am] YHWH your God\"). More generally for Dick, anokhi stands for self-\nawareness and consciousness. The Transmigration of Timothy Archer (1982)\nfeatures...",
      "seg_title": "The Exegesis of Philip K. Dick \u2014 Page 931",
      "segment_type": "page",
      "position": 931,
      "page_start": 931,
      "page_end": 931,
      "work_title": "The Exegesis of Philip K. Dick",
      "work_slug": "the-exegesis-of-philip-k-dick",
      "work_id": "PKD-WRK-1974-EXEGESIS"
    },
    {
      "seg_id": "PKD-SEG-EXEGESIS-P0940",
      "match_type": "exact_text",
      "matched_text": "awareness",
      "context_window": "... of capitalism's internal contradictions, and calling for a\nrevolutionary awareness among the working classes, Marx prophesied the end\nof the capitalist...",
      "seg_title": "The Exegesis of Philip K. Dick \u2014 Page 940",
      "segment_type": "page",
      "position": 940,
      "page_start": 940,
      "page_end": 940,
      "work_title": "The Exegesis of Philip K. Dick",
      "work_slug": "the-exegesis-of-philip-k-dick",
      "work_id": "PKD-WRK-1974-EXEGESIS"
    },
    {
      "seg_id": "PKD-SEG-EXEGESIS-P0998",
      "match_type": "exact_text",
      "matched_text": "awareness",
      "context_window": "... as \"ubiquitous.\" Hence Jesus then asks\nus to \"behold,\" to look with awareness: \"for, behold, the kingdom of God is\nwithin you.\" We are directed to...",
      "seg_title": "The Exegesis of Philip K. Dick \u2014 Page 998",
      "segment_type": "page",
      "position": 998,
      "page_start": 998,
      "page_end": 998,
      "work_title": "The Exegesis of Philip K. Dick",
      "work_slug": "the-exegesis-of-philip-k-dick",
      "work_id": "PKD-WRK-1974-EXEGESIS"
    },
    {
      "seg_id": "PKD-SEG-EXEGESIS-P1033",
      "match_type": "exact_text",
      "matched_text": "awareness",
      "context_window": "... quest to describe the extraordinary unity of\nwhat is, we can focus our awareness on ordinary reality and explore not only\nthe \"slings and arrows of...",
      "seg_title": "The Exegesis of Philip K. Dick \u2014 Page 1033",
      "segment_type": "page",
      "position": 1033,
      "page_start": 1033,
      "page_end": 1033,
      "work_title": "The Exegesis of Philip K. Dick",
      "work_slug": "the-exegesis-of-philip-k-dick",
      "work_id": "PKD-WRK-1974-EXEGESIS"
    },
    {
      "seg_id": "PKD-SEG-COSMCOSM-P0001",
      "match_type": "exact_text",
      "matched_text": "awareness",
      "context_window": "... that guides, programs, and generally controls us as we act\nwithout awareness of it within our projected world. The artifact, which I call\u00a0Zebra, has...",
      "seg_title": "Cosmogony and Cosmology \u2014 Page 1",
      "segment_type": "page",
      "position": 1,
      "page_start": 1,
      "page_end": 1,
      "work_title": "Cosmogony and Cosmology",
      "work_slug": "cosmogony-and-cosmology",
      "work_id": "PKD-WRK-1978-COSMCOSM"
    },
    {
      "seg_id": "PKD-SEG-COSMCOSM-P0008",
      "match_type": "exact_text",
      "matched_text": "awareness",
      "context_window": "... back to Christ. I propose, further, that\nthe induced triggering off of awareness of the authentic substratum by the true, secret Christian\nChurch results...",
      "seg_title": "Cosmogony and Cosmology \u2014 Page 8",
      "segment_type": "page",
      "position": 8,
      "page_start": 8,
      "page_end": 8,
      "work_title": "Cosmogony and Cosmology",
      "work_slug": "cosmogony-and-cosmology",
      "work_id": "PKD-WRK-1978-COSMCOSM"
    },
    {
      "seg_id": "PKD-SEG-BUILDUNIVERSE-P0009",
      "match_type": "exact_text",
      "matched_text": "awareness",
      "context_window": "... them, and even express itself\nthrough those humans, even without their awareness.\nIn the writing of Flow M\\ Tears, back in 1970, there was one unusual...",
      "seg_title": "How to Build a Universe That Doesn't Fall Apart Two Days Later \u2014 Page 9",
      "segment_type": "page",
      "position": 9,
      "page_start": 9,
      "page_end": 9,
      "work_title": "How to Build a Universe That Doesn't Fall Apart Two Days Later",
      "work_slug": "how-to-build-a-universe-that-doesnt-fall-apart-two-days-later",
      "work_id": "PKD-WRK-1978-BUILDUNIVERSE"
    },
    {
      "seg_id": "PKD-SEG-COSMCOSM-P0013",
      "match_type": "exact_text",
      "matched_text": "awareness",
      "context_window": "... is no other path.\nThe maker is motivated to seek an instrument for self-awareness: This is the premise of this\npaper. And our reality was constructed to...",
      "seg_title": "Cosmogony and Cosmology \u2014 Page 13",
      "segment_type": "page",
      "position": 13,
      "page_start": 13,
      "page_end": 13,
      "work_title": "Cosmogony and Cosmology",
      "work_slug": "cosmogony-and-cosmology",
      "work_id": "PKD-WRK-1978-COSMCOSM"
    },
    {
      "seg_id": "PKD-SEG-COSMCOSM-P0030",
      "match_type": "exact_text",
      "matched_text": "awareness",
      "context_window": "... other invisible interventions have probably taken place without our awareness. The Urgrund\ndoes not advertise to the artifact that it is here. Suppose...",
      "seg_title": "Cosmogony and Cosmology \u2014 Page 30",
      "segment_type": "page",
      "position": 30,
      "page_start": 30,
      "page_end": 30,
      "work_title": "Cosmogony and Cosmology",
      "work_slug": "cosmogony-and-cosmology",
      "work_id": "PKD-WRK-1978-COSMCOSM"
    },
    {
      "seg_id": "PKD-SEG-VALISTRI-P0408",
      "match_type": "exact_text",
      "matched_text": "awareness",
      "context_window": "... It is necessary, in evaluating these things, to distinguish your\nawareness from that of which you are aware. I can say when I noticed it but\nthat is...",
      "seg_title": "The VALIS Trilogy \u2014 Page 408",
      "segment_type": "page",
      "position": 408,
      "page_start": 408,
      "page_end": 408,
      "work_title": "The VALIS Trilogy",
      "work_slug": "the-valis-trilogy",
      "work_id": "PKD-WRK-1981-VALISTRI"
    },
    {
      "seg_id": "PKD-SEG-VALISTRI-P0424",
      "match_type": "exact_text",
      "matched_text": "Awareness",
      "context_window": "... anokhi, and of course\nthe term \u2018anokhi\u2019 itself refers to the Pure Self-Awareness, which is to say,\nPure Consciousness of Yahweh, the God of the Hebrew...",
      "seg_title": "The VALIS Trilogy \u2014 Page 424",
      "segment_type": "page",
      "position": 424,
      "page_start": 424,
      "page_end": 424,
      "work_title": "The VALIS Trilogy",
      "work_slug": "the-valis-trilogy",
      "work_id": "PKD-WRK-1981-VALISTRI"
    },
    {
      "seg_id": "PKD-SEG-VALISTRI-P0460",
      "match_type": "exact_text",
      "matched_text": "awareness",
      "context_window": "... quartets, can without words change human beings in terms of their own\nawareness of themselves, in terms of their ontological nature? Schopenhauer\nbelieved",
      "seg_title": "The VALIS Trilogy \u2014 Page 460",
      "segment_type": "page",
      "position": 460,
      "page_start": 460,
      "page_end": 460,
      "work_title": "The VALIS Trilogy",
      "work_slug": "the-valis-trilogy",
      "work_id": "PKD-WRK-1981-VALISTRI"
    }
  ]
}